aeolus/__init__.py
aeolus/api.py
aeolus/database_operations.py
aeolus/decorators.py
aeolus/downloader.py
aeolus/meteorology.py
aeolus/registry.py
aeolus/transforms.py
aeolus/types.py
aeolus/sources/__init__.py
aeolus/sources/openaq.py
aeolus/sources/regulatory.py
aeolus_aq-0.1.1a0.dist-info/licenses/LICENCE
aeolus_aq-0.1.1a0.dist-info/METADATA
aeolus_aq-0.1.1a0.dist-info/WHEEL
aeolus_aq-0.1.1a0.dist-info/top_level.txt
aeolus_aq-0.1.1a0.dist-info/RECORD
