Metadata-Version: 2.4
Name: aeolus_aq
Version: 0.1.1a0
Summary: This module provides functions for downloading metadata and data files from
Author-email: Ruaraidh Dobson <ruaraidh.dobson@gmail.com>
License-Expression: GPL-3.0-or-later
Project-URL: Homepage, https://github.com/southlondonscientific/aeolus
Requires-Python: >=3.11
License-File: LICENCE
Requires-Dist: pandas>=2.3.3
Requires-Dist: rdata>=0.11
Requires-Dist: requests>=2.32.5
Requires-Dist: sqlmodel>=0.0.27
Requires-Dist: tenacity>=8.2.0
Provides-Extra: dev
Requires-Dist: pytest>=7.4.0; extra == "dev"
Requires-Dist: pytest-cov>=4.1.0; extra == "dev"
Requires-Dist: pytest-mock>=3.11.1; extra == "dev"
Requires-Dist: responses>=0.23.0; extra == "dev"
Requires-Dist: freezegun>=1.2.2; extra == "dev"
Dynamic: license-file
